RNAHyperFold/__init__.py
RNAHyperFold/hypergraph_folding/__init__.py
RNAHyperFold/hypergraph_folding/rna_folder.py
RNAHyperFold/hypergraph_folding/temperature_hypergraph.py
RNAHyperFold/incidence_producers/__init__.py
RNAHyperFold/incidence_producers/connector.py
RNAHyperFold/incidence_producers/forgi_incidence_producer.py
RNAHyperFold/incidence_producers/forna_incidence_producer.py
RNAHyperFold/incidence_producers/incidence_producer.py
RNAHyperFold/incidence_producers/temperature_incidence_producer.py
RNAHyperFold/incidence_producers/vienna_incidence_producer.py
RNAHyperFold/rna_stats/__init__.py
RNAHyperFold/rna_stats/hypergraph_analysis.py
RNAHyperFold/rna_stats/rna_analyst.py
RNAHyperFold-0.1.0.dist-info/LICENSE
RNAHyperFold-0.1.0.dist-info/METADATA
RNAHyperFold-0.1.0.dist-info/WHEEL
RNAHyperFold-0.1.0.dist-info/top_level.txt
RNAHyperFold-0.1.0.dist-info/RECORD
